devioc/__init__.py
devioc/log.py
devioc/models.py
devioc/version.py
devioc-2025.6.2.data/scripts/devioc-startproject
devioc-2025.6.2.dist-info/METADATA
devioc-2025.6.2.dist-info/WHEEL
devioc-2025.6.2.dist-info/licenses/LICENSE
devioc-2025.6.2.dist-info/RECORD
