Metadata-Version: 2.4
Name: devioc
Version: 2025.6.2
Summary: Simple Python Device IOC Support for EPICS
License-Expression: MIT
License-File: LICENSE
Author: Michel Fodje
Author-email: michel4j@gmail.com
Requires-Python: >=3.9,<4.0
Classifier: Intended Audience :: Developers
Classifier: License :: OSI Approved :: MIT License
Classifier: Operating System :: OS Independent
Classifier: Programming Language :: Python
Classifier: Programming Language :: Python :: 3
Classifier: Programming Language :: Python :: 3.9
Classifier: Programming Language :: Python :: 3.10
Classifier: Programming Language :: Python :: 3.11
Classifier: Programming Language :: Python :: 3.12
Classifier: Programming Language :: Python :: 3.13
Classifier: Topic :: Software Development :: Libraries :: Application Frameworks
Classifier: Topic :: Software Development :: Libraries :: Python Modules
Requires-Dist: PyGObject (>=3.44.2,<4.0.0)
Requires-Dist: Twisted
Requires-Dist: gepics (>=2025.10.3,<2026.0.0)
Requires-Dist: numpy (>=1.2.0,<3.0.0)
Project-URL: Homepage, https://github.com/michel4j/devioc
Project-URL: Issues, https://github.com/michel4j/devioc/issues
